MANIFEST.in
README.md
setup.py
gym_morph/__init__.py
gym_morph/ant.xml
gym_morph/env.py
gym_morph/model.py
gym_morph.egg-info/PKG-INFO
gym_morph.egg-info/SOURCES.txt
gym_morph.egg-info/dependency_links.txt
gym_morph.egg-info/requires.txt
gym_morph.egg-info/top_level.txt