Metadata-Version: 1.0
Name: gym-morph
Version: 0.0.4
Summary: Gym mujoco environments with morphology-control
Home-page: UNKNOWN
Author: Alex Ray
Author-email: a@machinaut.com
License: UNKNOWN
Platform: UNKNOWN
